{"StartAt": "START SERVICEMAX COMPACTION JOBS", "States": {"START SERVICEMAX COMPACTION JOBS": {"Type": "Pass", "InputPath": "$", "ResultPath": "$", "Next": "GET LAMBDA"}, "GET LAMBDA": {"Type": "Choice", "Choices": [{"Variable": "$.INPUT.GET_LAMBDA", "StringEquals": "Y", "Next": "SKIP GET LAMBDA"}], "Default": "EXECUTE GET LAMBDA"}, "EXECUTE GET LAMBDA": {"Type": "Task", "InputPath": "$", "ResultPath": "$.INPUT.BATCH_NUMBER", "Resource": "arn:aws:lambda:us-east-1:541574621075:function:ddb_get_lambda", "Next": "SKIP GET LAMBDA"}, "SKIP GET LAMBDA": {"Type": "Pass", "InputPath": "$", "ResultPath": "$.SKIP_LAMBDA", "Next": "StartParallel"}, "StartParallel": {"Type": "Parallel", "Next": "Completed", "ResultPath": "$.parallelResult", "Branches": [{"StartAt": "SERVICEMAX_PRODUCT2", "States": {"SERVICEMAX_PRODUCT2": {"Type": "Choice", "Choices": [{"Variable": "$.INPUT.job_lnd_mrr_incr_refresh_ov_servicemax_product2", "StringEquals": "Y", "Next": "PASS SERVICEMAX_PRODUCT2"}], "Default": "LOAD SERVICEMAX_PRODUCT2"}, "LOAD SERVICEMAX_PRODUCT2": {"Type": "Task", "ResultPath": "$.SERVICEMAX_PRODUCT2", "Resource": "arn:aws:states:::glue:startJobRun.sync", "Parameters": {"JobName": "job_lnd_mrr_incr_refresh_ov_servicemax_product2", "Arguments": {"--batch_number.$": "$.INPUT.BATCH_NUMBER"}}, "Retry": [{"ErrorEquals": ["States.Timeout"], "MaxAttempts": 3, "IntervalSeconds": 60, "BackoffRate": 2}], "Catch": [{"ErrorEquals": ["States.TaskFailed"], "Next": "SNS_SERVICEMAX_PRODUCT2_FAILED"}], "Next": "PASS SERVICEMAX_PRODUCT2"}, "SNS_SERVICEMAX_PRODUCT2_FAILED": {"Type": "Task", "Resource": "arn:aws:states:::sns:publish", "Parameters": {"TopicArn": "arn:aws:sns:us-east-1:541574621075:ODP_SFN_FAILURE", "Message.$": "$.Cause", "Subject": " AWS Glue job for SERVICEMAX_PRODUCT2 Failed!"}, "Next": "SERVICEMAX_PRODUCT2_ACTIVITY"}, "SERVICEMAX_PRODUCT2_ACTIVITY": {"Type": "Task", "Resource": "arn:aws:states:us-east-1:541574621075:activity:COMPACTION_SERVICEMAX_PRODUCT2_ACTIVITY", "End": true}, "PASS SERVICEMAX_PRODUCT2": {"Type": "Pass", "End": true}}}, {"StartAt": "SERVICEMAX_SVMXC_SITE_C", "States": {"SERVICEMAX_SVMXC_SITE_C": {"Type": "Choice", "Choices": [{"Variable": "$.INPUT.job_lnd_mrr_incr_refresh_ov_servicemax_svmxc__site__c", "StringEquals": "Y", "Next": "PASS SERVICEMAX_SVMXC_SITE_C"}], "Default": "LOAD SERVICEMAX_SVMXC_SITE_C"}, "LOAD SERVICEMAX_SVMXC_SITE_C": {"Type": "Task", "Resource": "arn:aws:states:::glue:startJobRun.sync", "ResultPath": "$.SERVICEMAX_SVMXC_SITE_C", "Parameters": {"JobName": "job_lnd_mrr_incr_refresh_ov_servicemax_svmxc__site__c", "Arguments": {"--batch_number.$": "$.INPUT.BATCH_NUMBER"}}, "Retry": [{"ErrorEquals": ["States.Timeout"], "MaxAttempts": 3, "IntervalSeconds": 60, "BackoffRate": 2}], "Catch": [{"ErrorEquals": ["States.TaskFailed"], "Next": "SNS_SERVICEMAX_SVMXC_SITE_C_FAILED"}], "Next": "PASS SERVICEMAX_SVMXC_SITE_C"}, "SNS_SERVICEMAX_SVMXC_SITE_C_FAILED": {"Type": "Task", "Resource": "arn:aws:states:::sns:publish", "Parameters": {"TopicArn": "arn:aws:sns:us-east-1:541574621075:ODP_SFN_FAILURE", "Message.$": "$.Cause", "Subject": " AWS Glue job for SERVICEMAX_SVMXC_SITE_C Failed!"}, "Next": "SERVICEMAX_SVMXC_SITE_C_ACTIVITY"}, "SERVICEMAX_SVMXC_SITE_C_ACTIVITY": {"Type": "Task", "Resource": "arn:aws:states:us-east-1:541574621075:activity:COMPACTION_SERVICEMAX_SVMXC_SITE_C_ACTIVITY", "End": true}, "PASS SERVICEMAX_SVMXC_SITE_C": {"Type": "Pass", "End": true}}}, {"StartAt": "SERVICEMAX_ACCOUNT", "States": {"SERVICEMAX_ACCOUNT": {"Type": "Choice", "Choices": [{"Variable": "$.INPUT.job_lnd_mrr_incr_refresh_ov_servicemax_account", "StringEquals": "Y", "Next": "PASS SERVICEMAX_ACCOUNT"}], "Default": "LOAD SERVICEMAX_ACCOUNT"}, "LOAD SERVICEMAX_ACCOUNT": {"Type": "Task", "Resource": "arn:aws:states:::glue:startJobRun.sync", "ResultPath": "$.SERVICEMAX_ACCOUNT", "Parameters": {"JobName": "job_lnd_mrr_incr_refresh_ov_servicemax_account", "Arguments": {"--batch_number.$": "$.INPUT.BATCH_NUMBER"}}, "Retry": [{"ErrorEquals": ["States.Timeout"], "MaxAttempts": 3, "IntervalSeconds": 60, "BackoffRate": 2}], "Catch": [{"ErrorEquals": ["States.TaskFailed"], "Next": "SNS_SERVICEMAX_ACCOUNT_FAILED"}], "Next": "PASS SERVICEMAX_ACCOUNT"}, "SNS_SERVICEMAX_ACCOUNT_FAILED": {"Type": "Task", "Resource": "arn:aws:states:::sns:publish", "Parameters": {"TopicArn": "arn:aws:sns:us-east-1:541574621075:ODP_SFN_FAILURE", "Message.$": "$.Cause", "Subject": " AWS Glue job for SERVICEMAX_ACCOUNT Failed!"}, "Next": "SERVICEMAX_ACCOUNT_ACTIVITY"}, "SERVICEMAX_ACCOUNT_ACTIVITY": {"Type": "Task", "Resource": "arn:aws:states:us-east-1:541574621075:activity:COMPACTION_SERVICEMAX_ACCOUNT_ACTIVITY", "End": true}, "PASS SERVICEMAX_ACCOUNT": {"Type": "Pass", "End": true}}}, {"StartAt": "SERVICEMAX_INSTALLED_PRODUCT_C1", "States": {"SERVICEMAX_INSTALLED_PRODUCT_C1": {"Type": "Choice", "Choices": [{"Variable": "$.INPUT.job_lnd_mrr_incr_refresh_ov_servicemax_svmxc__installed_product__c1", "StringEquals": "Y", "Next": "PASS SERVICEMAX_INSTALLED_PRODUCT_C1"}], "Default": "LOAD SERVICEMAX_INSTALLED_PRODUCT_C1"}, "LOAD SERVICEMAX_INSTALLED_PRODUCT_C1": {"Type": "Task", "Resource": "arn:aws:states:::glue:startJobRun.sync", "ResultPath": "$.SERVICEMAX_INSTALLED_PRODUCT_C1", "Parameters": {"JobName": "job_lnd_mrr_incr_refresh_ov_servicemax_svmxc__installed_product__c1", "Arguments": {"--batch_number.$": "$.INPUT.BATCH_NUMBER"}}, "Retry": [{"ErrorEquals": ["States.Timeout"], "MaxAttempts": 3, "IntervalSeconds": 60, "BackoffRate": 2}], "Catch": [{"ErrorEquals": ["States.TaskFailed"], "Next": "SNS_SERVICEMAX_INSTALLED_PRODUCT_C1_FAILED"}], "Next": "PASS SERVICEMAX_INSTALLED_PRODUCT_C1"}, "SNS_SERVICEMAX_INSTALLED_PRODUCT_C1_FAILED": {"Type": "Task", "Resource": "arn:aws:states:::sns:publish", "Parameters": {"TopicArn": "arn:aws:sns:us-east-1:541574621075:ODP_SFN_FAILURE", "Message.$": "$.Cause", "Subject": " AWS Glue job for SERVICEMAX_INSTALLED_PRODUCT_C1 Failed!"}, "Next": "SERVICEMAX_INSTALLED_PRODUCT_C1_ACTIVITY"}, "SERVICEMAX_INSTALLED_PRODUCT_C1_ACTIVITY": {"Type": "Task", "Resource": "arn:aws:states:us-east-1:541574621075:activity:COMPACTION_SERVICEMAX_SVMXC__INSTALLED_PRODUCT__C1_ACTIVITY", "End": true}, "PASS SERVICEMAX_INSTALLED_PRODUCT_C1": {"Type": "Pass", "End": true}}}, {"StartAt": "SVMXC__INSTALLED_PRODUCT__C2", "States": {"SVMXC__INSTALLED_PRODUCT__C2": {"Type": "Choice", "Choices": [{"Variable": "$.INPUT.job_lnd_mrr_incr_refresh_ov_servicemax_svmxc__installed_product__c2", "StringEquals": "Y", "Next": "PASS SVMXC__INSTALLED_PRODUCT__C2"}], "Default": "LOAD SVMXC__INSTALLED_PRODUCT__C2"}, "LOAD SVMXC__INSTALLED_PRODUCT__C2": {"Type": "Task", "Resource": "arn:aws:states:::glue:startJobRun.sync", "ResultPath": "$.SVMXC__INSTALLED_PRODUCT__C2", "Parameters": {"JobName": "job_lnd_mrr_incr_refresh_ov_servicemax_svmxc__installed_product__c2", "Arguments": {"--batch_number.$": "$.INPUT.BATCH_NUMBER"}}, "Retry": [{"ErrorEquals": ["States.Timeout"], "MaxAttempts": 3, "IntervalSeconds": 60, "BackoffRate": 2}], "Catch": [{"ErrorEquals": ["States.TaskFailed"], "Next": "SNS_SVMXC__INSTALLED_PRODUCT__C2_FAILED"}], "Next": "PASS SVMXC__INSTALLED_PRODUCT__C2"}, "SNS_SVMXC__INSTALLED_PRODUCT__C2_FAILED": {"Type": "Task", "Resource": "arn:aws:states:::sns:publish", "Parameters": {"TopicArn": "arn:aws:sns:us-east-1:541574621075:ODP_SFN_FAILURE", "Message.$": "$.Cause", "Subject": " AWS Glue job for SVMXC__INSTALLED_PRODUCT__C2 Failed!"}, "Next": "SVMXC__INSTALLED_PRODUCT__C2_ACTIVITY"}, "SVMXC__INSTALLED_PRODUCT__C2_ACTIVITY": {"Type": "Task", "Resource": "arn:aws:states:us-east-1:541574621075:activity:COMPACTION_SERVICEMAX_SVMXC__INSTALLED_PRODUCT__C2_ACTIVITY", "End": true}, "PASS SVMXC__INSTALLED_PRODUCT__C2": {"Type": "Pass", "End": true}}}, {"StartAt": "SERVICEMAX_INSTALLED_PRODUCT_C3", "States": {"SERVICEMAX_INSTALLED_PRODUCT_C3": {"Type": "Choice", "Choices": [{"Variable": "$.INPUT.job_lnd_mrr_incr_refresh_ov_servicemax_svmxc__installed_product__c3", "StringEquals": "Y", "Next": "PASS SERVICEMAX_INSTALLED_PRODUCT_C3"}], "Default": "LOAD SERVICEMAX_INSTALLED_PRODUCT_C3"}, "LOAD SERVICEMAX_INSTALLED_PRODUCT_C3": {"Type": "Task", "Resource": "arn:aws:states:::glue:startJobRun.sync", "ResultPath": "$.SERVICEMAX_INSTALLED_PRODUCT_C3", "Parameters": {"JobName": "job_lnd_mrr_incr_refresh_ov_servicemax_svmxc__installed_product__c3", "Arguments": {"--batch_number.$": "$.INPUT.BATCH_NUMBER"}}, "Retry": [{"ErrorEquals": ["States.Timeout"], "MaxAttempts": 3, "IntervalSeconds": 60, "BackoffRate": 2}], "Catch": [{"ErrorEquals": ["States.TaskFailed"], "Next": "SNS_SERVICEMAX_INSTALLED_PRODUCT_C3_FAILED"}], "Next": "PASS SERVICEMAX_INSTALLED_PRODUCT_C3"}, "SNS_SERVICEMAX_INSTALLED_PRODUCT_C3_FAILED": {"Type": "Task", "Resource": "arn:aws:states:::sns:publish", "Parameters": {"TopicArn": "arn:aws:sns:us-east-1:541574621075:ODP_SFN_FAILURE", "Message.$": "$.Cause", "Subject": " AWS Glue job for SERVICEMAX_INSTALLED_PRODUCT_C3 Failed!"}, "Next": "SERVICEMAX_INSTALLED_PRODUCT_C3_ACTIVITY"}, "SERVICEMAX_INSTALLED_PRODUCT_C3_ACTIVITY": {"Type": "Task", "Resource": "arn:aws:states:us-east-1:541574621075:activity:COMPACTION_SERVICEMAX_SVMXC_INSTALLED_PRODUCT_C3_ACTIVITY", "End": true}, "PASS SERVICEMAX_INSTALLED_PRODUCT_C3": {"Type": "Pass", "End": true}}}, {"StartAt": "SERVICEMAX_INSTALLED_PRODUCT_C4", "States": {"SERVICEMAX_INSTALLED_PRODUCT_C4": {"Type": "Choice", "Choices": [{"Variable": "$.INPUT.job_lnd_mrr_incr_refresh_ov_servicemax_svmxc__installed_product__c4", "StringEquals": "Y", "Next": "PASS SERVICEMAX_INSTALLED_PRODUCT_C4"}], "Default": "LOAD SERVICEMAX_INSTALLED_PRODUCT_C4"}, "LOAD SERVICEMAX_INSTALLED_PRODUCT_C4": {"Type": "Task", "Resource": "arn:aws:states:::glue:startJobRun.sync", "ResultPath": "$.SERVICEMAX_INSTALLED_PRODUCT_C4", "Parameters": {"JobName": "job_lnd_mrr_incr_refresh_ov_servicemax_svmxc__installed_product__c4", "Arguments": {"--batch_number.$": "$.INPUT.BATCH_NUMBER"}}, "Retry": [{"ErrorEquals": ["States.Timeout"], "MaxAttempts": 3, "IntervalSeconds": 60, "BackoffRate": 2}], "Catch": [{"ErrorEquals": ["States.TaskFailed"], "Next": "SNS_SERVICEMAX_INSTALLED_PRODUCT_C4_FAILED"}], "Next": "PASS SERVICEMAX_INSTALLED_PRODUCT_C4"}, "SNS_SERVICEMAX_INSTALLED_PRODUCT_C4_FAILED": {"Type": "Task", "Resource": "arn:aws:states:::sns:publish", "Parameters": {"TopicArn": "arn:aws:sns:us-east-1:541574621075:ODP_SFN_FAILURE", "Message.$": "$.Cause", "Subject": " AWS Glue job for SERVICEMAX_INSTALLED_PRODUCT_C4 Failed!"}, "Next": "SERVICEMAX_INSTALLED_PRODUCT_C4_ACTIVITY"}, "SERVICEMAX_INSTALLED_PRODUCT_C4_ACTIVITY": {"Type": "Task", "Resource": "arn:aws:states:us-east-1:541574621075:activity:COMPACTION_SERVICEMAX_SVMXC_INSTALLED_PRODUCT_C4_ACTIVITY", "End": true}, "PASS SERVICEMAX_INSTALLED_PRODUCT_C4": {"Type": "Pass", "End": true}}}, {"StartAt": "SERVICEMAX_SERVICE_GROUP_C", "States": {"SERVICEMAX_SERVICE_GROUP_C": {"Type": "Choice", "Choices": [{"Variable": "$.INPUT.job_lnd_mrr_incr_refresh_ov_servicemax_svmxc__service_group__c", "StringEquals": "Y", "Next": "PASS SERVICEMAX_SERVICE_GROUP_C"}], "Default": "LOAD SERVICEMAX_SERVICE_GROUP_C"}, "LOAD SERVICEMAX_SERVICE_GROUP_C": {"Type": "Task", "Resource": "arn:aws:states:::glue:startJobRun.sync", "ResultPath": "$.SERVICEMAX_SERVICE_GROUP_C", "Parameters": {"JobName": "job_lnd_mrr_incr_refresh_ov_servicemax_svmxc__service_group__c", "Arguments": {"--batch_number.$": "$.INPUT.BATCH_NUMBER"}}, "Retry": [{"ErrorEquals": ["States.Timeout"], "MaxAttempts": 3, "IntervalSeconds": 60, "BackoffRate": 2}], "Catch": [{"ErrorEquals": ["States.TaskFailed"], "Next": "SNS_SERVICEMAX_SERVICE_GROUP_C_FAILED"}], "Next": "PASS SERVICEMAX_SERVICE_GROUP_C"}, "SNS_SERVICEMAX_SERVICE_GROUP_C_FAILED": {"Type": "Task", "Resource": "arn:aws:states:::sns:publish", "Parameters": {"TopicArn": "arn:aws:sns:us-east-1:541574621075:ODP_SFN_FAILURE", "Message.$": "$.Cause", "Subject": " AWS Glue job for SERVICEMAX_SERVICE_GROUP_C Failed!"}, "Next": "SERVICEMAX_SERVICE_GROUP_C_ACTIVITY"}, "SERVICEMAX_SERVICE_GROUP_C_ACTIVITY": {"Type": "Task", "Resource": "arn:aws:states:us-east-1:541574621075:activity:COMPACTION_SERVICEMAX_SVMXC_SERVICE_GROUP_C_ACTIVITY", "End": true}, "PASS SERVICEMAX_SERVICE_GROUP_C": {"Type": "Pass", "End": true}}}, {"StartAt": "SERVICEMAX_CONTACT", "States": {"SERVICEMAX_CONTACT": {"Type": "Choice", "Choices": [{"Variable": "$.INPUT.job_lnd_mrr_incr_refresh_ov_servicemax_contact", "StringEquals": "Y", "Next": "PASS SERVICEMAX_CONTACT"}], "Default": "LOAD SERVICEMAX_CONTACT"}, "LOAD SERVICEMAX_CONTACT": {"Type": "Task", "Resource": "arn:aws:states:::glue:startJobRun.sync", "ResultPath": "$.SERVICEMAX_CONTACT", "Parameters": {"JobName": "job_lnd_mrr_incr_refresh_ov_servicemax_contact", "Arguments": {"--batch_number.$": "$.INPUT.BATCH_NUMBER"}}, "Retry": [{"ErrorEquals": ["States.Timeout"], "MaxAttempts": 3, "IntervalSeconds": 60, "BackoffRate": 2}], "Catch": [{"ErrorEquals": ["States.TaskFailed"], "Next": "SNS_SERVICEMAX_CONTACT_FAILED"}], "Next": "PASS SERVICEMAX_CONTACT"}, "SNS_SERVICEMAX_CONTACT_FAILED": {"Type": "Task", "Resource": "arn:aws:states:::sns:publish", "Parameters": {"TopicArn": "arn:aws:sns:us-east-1:541574621075:ODP_SFN_FAILURE", "Message.$": "$.Cause", "Subject": " AWS Glue job for SERVICEMAX_CONTACT Failed!"}, "Next": "SERVICEMAX_CONTACT_ACTIVITY"}, "SERVICEMAX_CONTACT_ACTIVITY": {"Type": "Task", "Resource": "arn:aws:states:us-east-1:541574621075:activity:COMPACTION_SERVICEMAX_CONTACT_ACTIVITY", "End": true}, "PASS SERVICEMAX_CONTACT": {"Type": "Pass", "End": true}}}]}, "Completed": {"Type": "Pass", "InputPath": "$.SKIP_LAMBDA", "Next": "SNS_SERVICEMAX_COMPACTION_STATUS"}, "SNS_SERVICEMAX_COMPACTION_STATUS": {"Type": "Task", "InputPath": "$", "ResultPath": "$.snsResult", "Resource": "arn:aws:states:::sns:publish", "Parameters": {"TopicArn": "arn:aws:sns:us-east-1:541574621075:ODP_SFN_SUCCESS", "Message": {"Subject": "AWS Step function for SERVICEMAX_COMPACTION completed successfully!!"}}, "End": true}}}