{"StartAt": "START GLPROD ONHAND COMPACTION JOBS", "States": {"START GLPROD ONHAND COMPACTION JOBS": {"Type": "Pass", "InputPath": "$", "ResultPath": "$.start", "Next": "GET LAMBDA"}, "GET LAMBDA": {"Type": "Choice", "Choices": [{"Variable": "$.INPUT.GET_LAMBDA", "StringEquals": "Y", "Next": "SKIP GET LAMBDA"}], "Default": "EXECUTE GET LAMBDA"}, "EXECUTE GET LAMBDA": {"Type": "Task", "InputPath": "$", "ResultPath": "$.INPUT.BATCH_NUMBER", "Resource": "arn:aws:lambda:us-east-1:541574621075:function:ddb_get_lambda", "Next": "SKIP GET LAMBDA"}, "SKIP GET LAMBDA": {"Type": "Pass", "InputPath": "$", "ResultPath": "$.SKIP_LAMBDA", "Next": "StartParallel"}, "StartParallel": {"Type": "Parallel", "ResultPath": "$.parallelResult", "Branches": [{"StartAt": "GLPROD_MTL_ONHAND_QUANTITIES_DETAIL", "States": {"GLPROD_MTL_ONHAND_QUANTITIES_DETAIL": {"Type": "Choice", "Choices": [{"Variable": "$.INPUT.job_lnd_mrr_incr_refresh_op_val_intrdy_glprod_mtl_onhand_quantities_detail", "StringEquals": "Y", "Next": "PASS GLPROD_MTL_ONHAND_QUANTITIES_DETAIL"}], "Default": "LOAD GLPROD_MTL_ONHAND_QUANTITIES_DETAIL"}, "LOAD GLPROD_MTL_ONHAND_QUANTITIES_DETAIL": {"Type": "Task", "Resource": "arn:aws:states:::glue:startJobRun.sync", "Parameters": {"JobName": "job_lnd_mrr_incr_refresh_op_val_intrdy_glprod_mtl_onhand_quantities_detail", "Arguments": {"--batch_number.$": "$.INPUT.BATCH_NUMBER"}}, "Retry": [{"ErrorEquals": ["States.Timeout"], "MaxAttempts": 3, "IntervalSeconds": 60, "BackoffRate": 2}], "Catch": [{"ErrorEquals": ["States.TaskFailed"], "Next": "SNS_GLPROD_MTL_ONHAND_QUANTITIES_DETAIL_FAILED"}], "Next": "PASS GLPROD_MTL_ONHAND_QUANTITIES_DETAIL"}, "SNS_GLPROD_MTL_ONHAND_QUANTITIES_DETAIL_FAILED": {"Type": "Task", "Resource": "arn:aws:states:::sns:publish", "Parameters": {"TopicArn": "arn:aws:sns:us-east-1:541574621075:ODP_SFN_FAILURE", "Message.$": "$.Cause", "Subject": " AWS Glue job for GLPROD_MTL_ONHAND_QUANTITIES_DETAIL Failed!"}, "Next": "GLPROD_MTL_ONHAND_QUANTITIES_DETAIL_ACTIVITY"}, "GLPROD_MTL_ONHAND_QUANTITIES_DETAIL_ACTIVITY": {"Type": "Task", "Resource": "arn:aws:states:us-east-1:541574621075:activity:COMPACTION_MAPP_GLPROD_MTL_ONHAND_QUANTITIES_DETAIL_INTRADAY_ACTIVITY", "End": true}, "PASS GLPROD_MTL_ONHAND_QUANTITIES_DETAIL": {"Type": "Pass", "End": true}}}, {"StartAt": "GLPROD_MTL_RESERVATIONS", "States": {"GLPROD_MTL_RESERVATIONS": {"Type": "Choice", "Choices": [{"Variable": "$.INPUT.job_lnd_mrr_incr_refresh_op_val_intrdy_glprod_mtl_reservations", "StringEquals": "Y", "Next": "PASS GLPROD_MTL_RESERVATIONS"}], "Default": "LOAD GLPROD_MTL_RESERVATIONS"}, "LOAD GLPROD_MTL_RESERVATIONS": {"Type": "Task", "Resource": "arn:aws:states:::glue:startJobRun.sync", "Parameters": {"JobName": "job_lnd_mrr_incr_refresh_op_val_intrdy_glprod_mtl_reservations", "Arguments": {"--batch_number.$": "$.INPUT.BATCH_NUMBER"}}, "Retry": [{"ErrorEquals": ["States.Timeout"], "MaxAttempts": 3, "IntervalSeconds": 60, "BackoffRate": 2}], "Catch": [{"ErrorEquals": ["States.TaskFailed"], "Next": "SNS_GLPROD_MTL_RESERVATIONS_FAILED"}], "Next": "PASS GLPROD_MTL_RESERVATIONS"}, "SNS_GLPROD_MTL_RESERVATIONS_FAILED": {"Type": "Task", "Resource": "arn:aws:states:::sns:publish", "Parameters": {"TopicArn": "arn:aws:sns:us-east-1:541574621075:ODP_SFN_FAILURE", "Message.$": "$.Cause", "Subject": " AWS Glue job for GLPROD_MTL_RESERVATIONS Failed!"}, "Next": "GLPROD_MTL_RESERVATIONS_ACTIVITY"}, "GLPROD_MTL_RESERVATIONS_ACTIVITY": {"Type": "Task", "Resource": "arn:aws:states:us-east-1:541574621075:activity:COMPACTION_MAPP_GLPROD_MTL_RESERVATIONS_INTRADAY_ACTIVITY", "End": true}, "PASS GLPROD_MTL_RESERVATIONS": {"Type": "Pass", "End": true}}}, {"StartAt": "GLPROD_GL_LEDGERS", "States": {"GLPROD_GL_LEDGERS": {"Type": "Choice", "Choices": [{"Variable": "$.INPUT.job_lnd_mrr_incr_refresh_op_val_intrdy_glprod_gl_ledgers", "StringEquals": "Y", "Next": "PASS GLPROD_GL_LEDGERS"}], "Default": "LOAD GLPROD_GL_LEDGERS"}, "LOAD GLPROD_GL_LEDGERS": {"Type": "Task", "Resource": "arn:aws:states:::glue:startJobRun.sync", "Parameters": {"JobName": "job_lnd_mrr_incr_refresh_op_val_intrdy_glprod_gl_ledgers", "Arguments": {"--batch_number.$": "$.INPUT.BATCH_NUMBER"}}, "Retry": [{"ErrorEquals": ["States.Timeout"], "MaxAttempts": 3, "IntervalSeconds": 60, "BackoffRate": 2}], "Catch": [{"ErrorEquals": ["States.TaskFailed"], "Next": "SNS_GLPROD_GL_LEDGERS_FAILED"}], "Next": "PASS GLPROD_GL_LEDGERS"}, "SNS_GLPROD_GL_LEDGERS_FAILED": {"Type": "Task", "Resource": "arn:aws:states:::sns:publish", "Parameters": {"TopicArn": "arn:aws:sns:us-east-1:541574621075:ODP_SFN_FAILURE", "Message.$": "$.Cause", "Subject": " AWS Glue job for GLPROD_GL_LEDGERS Failed!"}, "Next": "GLPROD_GL_LEDGERS_ACTIVITY"}, "GLPROD_GL_LEDGERS_ACTIVITY": {"Type": "Task", "Resource": "arn:aws:states:us-east-1:541574621075:activity:COMPACTION_MAPP_GLPROD_GL_LEDGERS_ACTIVITY", "End": true}, "PASS GLPROD_GL_LEDGERS": {"Type": "Pass", "End": true}}}], "Catch": [{"ErrorEquals": ["States.TaskFailed"], "Next": "Insert error log into redshift"}], "Next": "Put Lambda"}, "Insert error log into redshift": {"Type": "Task", "ResultPath": "$.logerror", "Resource": "arn:aws:states:::glue:startJobRun.sync", "Parameters": {"JobName": "job_mrr_redshift_log", "Arguments": {"--jobname": "MIRROR_COMPACTION_ORDER_FREQUENT", "--status": "JOB ERROR"}}, "Next": "Put Lambda"}, "Put Lambda": {"Type": "Choice", "Choices": [{"Variable": "$.INPUT.PUT_LAMBDA", "StringEquals": "Y", "Next": "Skip Put Lambda"}], "Default": "Execute Put Lambda"}, "Execute Put Lambda": {"Type": "Task", "InputPath": "$", "ResultPath": "$.putLambda", "Resource": "arn:aws:lambda:us-east-1:541574621075:function:ddb_put_lambda", "Next": "Skip Put Lambda"}, "Skip Put Lambda": {"Type": "Pass", "Next": "Completed"}, "Completed": {"Type": "Pass", "InputPath": "$.SKIP_LAMBDA", "Next": "SNS_MAPP_COMPACTION_GLPROD_ONHAND_INTRADAY2_SUCCESS"}, "SNS_MAPP_COMPACTION_GLPROD_ONHAND_INTRADAY2_SUCCESS": {"Type": "Task", "InputPath": "$", "ResultPath": "$.snsResult", "Resource": "arn:aws:states:::sns:publish", "Parameters": {"TopicArn": "arn:aws:sns:us-east-1:541574621075:ODP_SFN_SUCCESS", "Message": {"Subject": "AWS Step function for MAPP_COMPACTION_GLPROD_ONHAND_INTRADAY2 completed successfully!!"}}, "End": true}}}