{"StartAt": "START MAPP_ORDER_MASTER_SCHEDULE_INTRADAY", "States": {"START MAPP_ORDER_MASTER_SCHEDULE_INTRADAY": {"Type": "Pass", "InputPath": "$", "OutputPath": "$", "Next": "MAPP_ORDER_INTRADAY"}, "MAPP_ORDER_INTRADAY": {"Type": "Choice", "Choices": [{"Variable": "$.INPUT.MAPP_ORDER_INTRADAY", "StringEquals": "Y", "Next": "PASS MAPP_ORDER_INTRADAY"}], "Default": "LOAD MAPP_ORDER_INTRADAY"}, "LOAD MAPP_ORDER_INTRADAY": {"Type": "Task", "InputPath": "$", "ResultPath": "$.MAPP_ORDER_INTRADAY", "Resource": "arn:aws:states:::glue:startJobRun.sync", "Parameters": {"JobName": "job_mrr_entity_cds_rs_proc", "Arguments": {"--rs_proc_name": "hdl_services_sp.sp_mapp_hourly_order_wrapper()"}}, "Retry": [{"ErrorEquals": ["States.Timeout"], "MaxAttempts": 3, "IntervalSeconds": 60, "BackoffRate": 2}], "Catch": [{"ErrorEquals": ["States.TaskFailed"], "Next": "SNS_MAPP_ORDER_INTRADAY_FAILED"}], "Next": "PASS MAPP_ORDER_INTRADAY"}, "SNS_MAPP_ORDER_INTRADAY_FAILED": {"Type": "Task", "Resource": "arn:aws:states:::sns:publish", "Parameters": {"TopicArn": "arn:aws:sns:us-east-1:541574621075:ODP_SFN_FAILURE", "Message.$": "$.Cause", "Subject": " AWS Step Function for MAPP_ORDER_INTRADAY Failed!"}, "End": false}, "PASS MAPP_ORDER_INTRADAY": {"Type": "Pass", "Next": "Completed"}, "Completed": {"Type": "Pass", "Next": "SNS_MAPP_ORDER_MASTER_SCHEDULE_INTRADAY_SUCCESS"}, "SNS_MAPP_ORDER_MASTER_SCHEDULE_INTRADAY_SUCCESS": {"Type": "Task", "Resource": "arn:aws:states:::sns:publish", "Parameters": {"TopicArn": "arn:aws:sns:us-east-1:541574621075:ODP_SFN_SUCCESS", "Message": {"Subject": "AWS Step function for MAPP_ORDER_MASTER_SCHEDULE_INTRADAY completed successfully!!"}}, "End": true}}}