{"StartAt": "UPDATE SNAPSHOT LAMBDA", "States": {"UPDATE SNAPSHOT LAMBDA": {"Type": "Task", "ResultPath": "$.CHECK SNAPSHOT LAMBDA", "Parameters": {"DDB_KEY_TO_UPDATE": "daily_d"}, "Resource": "arn:aws:lambda:us-east-1:541574621075:function:mapp_snapshot_lock", "Next": "CHECK SNAPSHOT LAMBDA"}, "CHECK SNAPSHOT LAMBDA": {"Type": "Task", "ResultPath": "$.MAPP_UNSOURCED_SNAPSHOT_WRAPPER", "Parameters": {"DDB_KEY_TO_UPDATE": "daily_d_check"}, "Resource": "arn:aws:lambda:us-east-1:541574621075:function:mapp_snapshot_lock", "Catch": [{"ErrorEquals": ["ZeroDivisionError"], "Next": "SNS_SKIP_UNSOURCED_SNAPSHOT"}], "Next": "MAPP_UNSOURCED_SNAPSHOT_WRAPPER"}, "MAPP_UNSOURCED_SNAPSHOT_WRAPPER": {"Type": "Choice", "Choices": [{"Variable": "$.INPUT.MAPP_UNSOURCED_SNAPSHOT", "StringEquals": "Y", "Next": "SKIP MAPP_UNSOURCED_SNAPSHOT_WRAPPER"}], "Default": "LOAD MAPP_UNSOURCED_SNAPSHOT_WRAPPER"}, "LOAD MAPP_UNSOURCED_SNAPSHOT_WRAPPER": {"Type": "Task", "InputPath": "$", "ResultPath": "$.SNAPSHOT_BACKORDERS_CDS_UNSRCD_FS", "Resource": "arn:aws:states:::glue:startJobRun.sync", "Parameters": {"JobName": "job_mrr_entity_cds_rs_proc", "Arguments": {"--rs_proc_name": "hdl_services_sp.sp_mapp_unsourced_snapshot_wrapper()"}}, "Retry": [{"ErrorEquals": ["States.Timeout"], "MaxAttempts": 3, "IntervalSeconds": 60, "BackoffRate": 2}], "Catch": [{"ErrorEquals": ["States.TaskFailed"], "Next": "SNS_MAPP_UNSOURCED_SNAPSHOT_WRAPPER"}], "Next": "SKIP MAPP_UNSOURCED_SNAPSHOT_WRAPPER"}, "SNS_MAPP_UNSOURCED_SNAPSHOT_WRAPPER": {"Type": "Task", "Resource": "arn:aws:states:::sns:publish", "Parameters": {"TopicArn": "arn:aws:sns:us-east-1:541574621075:ODP_SFN_FAILURE", "Message.$": "$.Cause", "Subject": "AWS GLUE SHELL JOB FOR SNAPSHOT_BACKORDERS_CDS_UNSRCD_FS FAILED!"}, "End": false}, "SKIP MAPP_UNSOURCED_SNAPSHOT_WRAPPER": {"Type": "Pass", "Next": "Completed"}, "Completed": {"Type": "Pass", "Next": "SNS_MAPP_UNSOURCED_SNAPSHOT_SUCCESS"}, "SNS_MAPP_UNSOURCED_SNAPSHOT_SUCCESS": {"Type": "Task", "Resource": "arn:aws:states:::sns:publish", "Parameters": {"TopicArn": "arn:aws:sns:us-east-1:541574621075:ODP_SFN_SUCCESS", "Message": {"Subject": "AWS Step function for MAPP_UNSOURCED_SNAPSHOT completed successfully!!"}}, "End": true}, "SNS_SKIP_UNSOURCED_SNAPSHOT": {"Type": "Task", "Resource": "arn:aws:states:::sns:publish", "Parameters": {"TopicArn": "arn:aws:sns:us-east-1:541574621075:ODP_SFN_SUCCESS", "Message": {"Subject": "Skipping Unsourced Snapshot as Continengency is running!!"}}, "End": true}}}