{"StartAt": "START SIT COMPACTION JOBS", "States": {"START SIT COMPACTION JOBS": {"Type": "Pass", "InputPath": "$", "ResultPath": "$", "Next": "GET LAMBDA"}, "GET LAMBDA": {"Type": "Choice", "Choices": [{"Variable": "$.INPUT.GET_LAMBDA", "StringEquals": "Y", "Next": "SKIP GET LAMBDA"}], "Default": "EXECUTE GET LAMBDA"}, "EXECUTE GET LAMBDA": {"Type": "Task", "InputPath": "$", "ResultPath": "$.INPUT.BATCH_NUMBER", "Resource": "arn:aws:lambda:us-east-1:541574621075:function:ddb_get_lambda", "Next": "SKIP GET LAMBDA"}, "SKIP GET LAMBDA": {"Type": "Pass", "InputPath": "$", "ResultPath": "$.SKIP_LAMBDA", "Next": "StartParallel"}, "StartParallel": {"Type": "Parallel", "Next": "Completed", "ResultPath": "$.parallelResult", "Branches": [{"StartAt": "SIT_S_TIMEZONE", "States": {"SIT_S_TIMEZONE": {"Type": "Choice", "Choices": [{"Variable": "$.INPUT.job_lnd_mrr_incr_refresh_ov_sit_s_timezone", "StringEquals": "Y", "Next": "PASS SIT_S_TIMEZONE"}], "Default": "LOAD SIT_S_TIMEZONE"}, "LOAD SIT_S_TIMEZONE": {"Type": "Task", "ResultPath": "$.SIT_S_TIMEZONE", "Resource": "arn:aws:states:::glue:startJobRun.sync", "Parameters": {"JobName": "job_lnd_mrr_incr_refresh_ov_sit_s_timezone", "Arguments": {"--batch_number.$": "$.INPUT.BATCH_NUMBER"}}, "Retry": [{"ErrorEquals": ["States.Timeout"], "MaxAttempts": 3, "IntervalSeconds": 60, "BackoffRate": 2}], "Catch": [{"ErrorEquals": ["States.TaskFailed"], "Next": "SNS_SIT_S_TIMEZONE_FAILED"}], "Next": "PASS SIT_S_TIMEZONE"}, "SNS_SIT_S_TIMEZONE_FAILED": {"Type": "Task", "Resource": "arn:aws:states:::sns:publish", "Parameters": {"TopicArn": "arn:aws:sns:us-east-1:541574621075:ODP_SFN_FAILURE", "Message.$": "$.Cause", "Subject": " AWS Glue job for SNS_SIT_S_TIMEZONE Failed!"}, "Next": "SIT_S_TIMEZONE_ACTIVITY"}, "SIT_S_TIMEZONE_ACTIVITY": {"Type": "Task", "Resource": "arn:aws:states:us-east-1:541574621075:activity:COMPACTION_SIT_S_TIMEZONE_ACTIVITY", "End": true}, "PASS SIT_S_TIMEZONE": {"Type": "Pass", "End": true}}}, {"StartAt": "SIT_S_LST_OF_VAL", "States": {"SIT_S_LST_OF_VAL": {"Type": "Choice", "Choices": [{"Variable": "$.INPUT.job_lnd_mrr_incr_refresh_ov_sit_s_lst_of_val", "StringEquals": "Y", "Next": "PASS SIT_S_LST_OF_VAL"}], "Default": "LOAD SIT_S_LST_OF_VAL"}, "LOAD SIT_S_LST_OF_VAL": {"Type": "Task", "Resource": "arn:aws:states:::glue:startJobRun.sync", "ResultPath": "$.SIT_S_LST_OF_VAL", "Parameters": {"JobName": "job_lnd_mrr_incr_refresh_ov_sit_s_lst_of_val", "Arguments": {"--batch_number.$": "$.INPUT.BATCH_NUMBER"}}, "Retry": [{"ErrorEquals": ["States.Timeout"], "MaxAttempts": 3, "IntervalSeconds": 60, "BackoffRate": 2}], "Catch": [{"ErrorEquals": ["States.TaskFailed"], "Next": "SNS_SIT_S_LST_OF_VAL_FAILED"}], "Next": "PASS SIT_S_LST_OF_VAL"}, "SNS_SIT_S_LST_OF_VAL_FAILED": {"Type": "Task", "Resource": "arn:aws:states:::sns:publish", "Parameters": {"TopicArn": "arn:aws:sns:us-east-1:541574621075:ODP_SFN_FAILURE", "Message.$": "$.Cause", "Subject": " AWS Glue job for SIT_S_LST_OF_VAL Failed!"}, "Next": "SIT_S_LST_OF_VAL_ACTIVITY"}, "SIT_S_LST_OF_VAL_ACTIVITY": {"Type": "Task", "Resource": "arn:aws:states:us-east-1:541574621075:activity:COMPACTION_SIT_S_LST_OF_VAL_ACTIVITY", "End": true}, "PASS SIT_S_LST_OF_VAL": {"Type": "Pass", "End": true}}}, {"StartAt": "SIT_S_SRV_REQ_X", "States": {"SIT_S_SRV_REQ_X": {"Type": "Choice", "Choices": [{"Variable": "$.INPUT.job_lnd_mrr_incr_refresh_ov_sit_s_srv_req_x", "StringEquals": "Y", "Next": "PASS SIT_S_SRV_REQ_X"}], "Default": "LOAD SIT_S_SRV_REQ_X"}, "LOAD SIT_S_SRV_REQ_X": {"Type": "Task", "ResultPath": "$.SIT_S_SRV_REQ_X", "Resource": "arn:aws:states:::glue:startJobRun.sync", "Parameters": {"JobName": "job_lnd_mrr_incr_refresh_ov_sit_s_srv_req_x", "Arguments": {"--batch_number.$": "$.INPUT.BATCH_NUMBER"}}, "Retry": [{"ErrorEquals": ["States.Timeout"], "MaxAttempts": 3, "IntervalSeconds": 60, "BackoffRate": 2}], "Catch": [{"ErrorEquals": ["States.TaskFailed"], "Next": "SNS_SIT_S_SRV_REQ_X_FAILED"}], "Next": "PASS SIT_S_SRV_REQ_X"}, "SNS_SIT_S_SRV_REQ_X_FAILED": {"Type": "Task", "Resource": "arn:aws:states:::sns:publish", "Parameters": {"TopicArn": "arn:aws:sns:us-east-1:541574621075:ODP_SFN_FAILURE", "Message.$": "$.Cause", "Subject": " AWS Glue job for SNS_SIT_S_SRV_REQ_X Failed!"}, "Next": "SIT_S_SRV_REQ_X_ACTIVITY"}, "SIT_S_SRV_REQ_X_ACTIVITY": {"Type": "Task", "Resource": "arn:aws:states:us-east-1:541574621075:activity:COMPACTION_SIT_S_SRV_REQ_X_ACTIVITY", "End": true}, "PASS SIT_S_SRV_REQ_X": {"Type": "Pass", "End": true}}}, {"StartAt": "SIT_S_EVT_ACT", "States": {"SIT_S_EVT_ACT": {"Type": "Choice", "Choices": [{"Variable": "$.INPUT.job_lnd_mrr_incr_refresh_ov_sit_s_evt_act", "StringEquals": "Y", "Next": "PASS SIT_S_EVT_ACT"}], "Default": "LOAD SIT_S_EVT_ACT"}, "LOAD SIT_S_EVT_ACT": {"Type": "Task", "ResultPath": "$.SIT_S_EVT_ACT", "Resource": "arn:aws:states:::glue:startJobRun.sync", "Parameters": {"JobName": "job_lnd_mrr_incr_refresh_ov_sit_s_evt_act", "Arguments": {"--batch_number.$": "$.INPUT.BATCH_NUMBER"}}, "Retry": [{"ErrorEquals": ["States.Timeout"], "MaxAttempts": 3, "IntervalSeconds": 60, "BackoffRate": 2}], "Catch": [{"ErrorEquals": ["States.TaskFailed"], "Next": "SNS_SIT_S_EVT_ACT_FAILED"}], "Next": "PASS SIT_S_EVT_ACT"}, "SNS_SIT_S_EVT_ACT_FAILED": {"Type": "Task", "Resource": "arn:aws:states:::sns:publish", "Parameters": {"TopicArn": "arn:aws:sns:us-east-1:541574621075:ODP_SFN_FAILURE", "Message.$": "$.Cause", "Subject": " AWS Glue job for SNS_SIT_S_EVT_ACT Failed!"}, "Next": "SIT_S_EVT_ACT_ACTIVITY"}, "SIT_S_EVT_ACT_ACTIVITY": {"Type": "Task", "Resource": "arn:aws:states:us-east-1:541574621075:activity:COMPACTION_SIT_S_EVT_ACT_ACTIVITY", "End": true}, "PASS SIT_S_EVT_ACT": {"Type": "Pass", "End": true}}}, {"StartAt": "SIT_S_EVT_ACT_X", "States": {"SIT_S_EVT_ACT_X": {"Type": "Choice", "Choices": [{"Variable": "$.INPUT.job_lnd_mrr_incr_refresh_ov_sit_s_evt_act_x", "StringEquals": "Y", "Next": "PASS SIT_S_EVT_ACT_X"}], "Default": "LOAD SIT_S_EVT_ACT_X"}, "LOAD SIT_S_EVT_ACT_X": {"Type": "Task", "ResultPath": "$.SIT_S_EVT_ACT_X", "Resource": "arn:aws:states:::glue:startJobRun.sync", "Parameters": {"JobName": "job_lnd_mrr_incr_refresh_ov_sit_s_evt_act_x", "Arguments": {"--batch_number.$": "$.INPUT.BATCH_NUMBER"}}, "Retry": [{"ErrorEquals": ["States.Timeout"], "MaxAttempts": 3, "IntervalSeconds": 60, "BackoffRate": 2}], "Catch": [{"ErrorEquals": ["States.TaskFailed"], "Next": "SNS_SIT_S_EVT_ACT_X_FAILED"}], "Next": "PASS SIT_S_EVT_ACT_X"}, "SNS_SIT_S_EVT_ACT_X_FAILED": {"Type": "Task", "Resource": "arn:aws:states:::sns:publish", "Parameters": {"TopicArn": "arn:aws:sns:us-east-1:541574621075:ODP_SFN_FAILURE", "Message.$": "$.Cause", "Subject": " AWS Glue job for SNS_SIT_S_EVT_ACT_X Failed!"}, "Next": "SIT_S_EVT_ACT_X_ACTIVITY"}, "SIT_S_EVT_ACT_X_ACTIVITY": {"Type": "Task", "Resource": "arn:aws:states:us-east-1:541574621075:activity:COMPACTION_SIT_S_EVT_ACT_X_ACTIVITY", "End": true}, "PASS SIT_S_EVT_ACT_X": {"Type": "Pass", "End": true}}}, {"StartAt": "SIT_S_EVT_ACT_FNX", "States": {"SIT_S_EVT_ACT_FNX": {"Type": "Choice", "Choices": [{"Variable": "$.INPUT.job_lnd_mrr_incr_refresh_ov_sit_s_evt_act_fnx", "StringEquals": "Y", "Next": "PASS SIT_S_EVT_ACT_FNX"}], "Default": "LOAD SIT_S_EVT_ACT_FNX"}, "LOAD SIT_S_EVT_ACT_FNX": {"Type": "Task", "ResultPath": "$.SIT_S_EVT_ACT_FNX", "Resource": "arn:aws:states:::glue:startJobRun.sync", "Parameters": {"JobName": "job_lnd_mrr_incr_refresh_ov_sit_s_evt_act_fnx", "Arguments": {"--batch_number.$": "$.INPUT.BATCH_NUMBER"}}, "Retry": [{"ErrorEquals": ["States.Timeout"], "MaxAttempts": 3, "IntervalSeconds": 60, "BackoffRate": 2}], "Catch": [{"ErrorEquals": ["States.TaskFailed"], "Next": "SNS_SIT_S_EVT_ACT_FNX_FAILED"}], "Next": "PASS SIT_S_EVT_ACT_FNX"}, "SNS_SIT_S_EVT_ACT_FNX_FAILED": {"Type": "Task", "Resource": "arn:aws:states:::sns:publish", "Parameters": {"TopicArn": "arn:aws:sns:us-east-1:541574621075:ODP_SFN_FAILURE", "Message.$": "$.Cause", "Subject": " AWS Glue job for SNS_SIT_S_EVT_ACT_FNX Failed!"}, "Next": "SIT_S_EVT_ACT_FNX_ACTIVITY"}, "SIT_S_EVT_ACT_FNX_ACTIVITY": {"Type": "Task", "Resource": "arn:aws:states:us-east-1:541574621075:activity:COMPACTION_SIT_S_EVT_ACT_FNX_ACTIVITY", "End": true}, "PASS SIT_S_EVT_ACT_FNX": {"Type": "Pass", "End": true}}}, {"StartAt": "SIT_S_ACTPART_MVMT", "States": {"SIT_S_ACTPART_MVMT": {"Type": "Choice", "Choices": [{"Variable": "$.INPUT.job_lnd_mrr_incr_refresh_ov_sit_s_actpart_mvmt", "StringEquals": "Y", "Next": "PASS SIT_S_ACTPART_MVMT"}], "Default": "LOAD SIT_S_ACTPART_MVMT"}, "LOAD SIT_S_ACTPART_MVMT": {"Type": "Task", "ResultPath": "$.SIT_S_ACTPART_MVMT", "Resource": "arn:aws:states:::glue:startJobRun.sync", "Parameters": {"JobName": "job_lnd_mrr_incr_refresh_ov_sit_s_actpart_mvmt", "Arguments": {"--batch_number.$": "$.INPUT.BATCH_NUMBER"}}, "Retry": [{"ErrorEquals": ["States.Timeout"], "MaxAttempts": 3, "IntervalSeconds": 60, "BackoffRate": 2}], "Catch": [{"ErrorEquals": ["States.TaskFailed"], "Next": "SNS_SIT_S_ACTPART_MVMT_FAILED"}], "Next": "PASS SIT_S_ACTPART_MVMT"}, "SNS_SIT_S_ACTPART_MVMT_FAILED": {"Type": "Task", "Resource": "arn:aws:states:::sns:publish", "Parameters": {"TopicArn": "arn:aws:sns:us-east-1:541574621075:ODP_SFN_FAILURE", "Message.$": "$.Cause", "Subject": " AWS Glue job for SNS_SIT_S_ACTPART_MVMT Failed!"}, "Next": "SIT_S_ACTPART_MVMT_ACTIVITY"}, "SIT_S_ACTPART_MVMT_ACTIVITY": {"Type": "Task", "Resource": "arn:aws:states:us-east-1:541574621075:activity:COMPACTION_SIT_S_ACTPART_MVMT_ACTIVITY", "End": true}, "PASS SIT_S_ACTPART_MVMT": {"Type": "Pass", "End": true}}}, {"StartAt": "SIT_S_TMSHT_ITEM", "States": {"SIT_S_TMSHT_ITEM": {"Type": "Choice", "Choices": [{"Variable": "$.INPUT.job_lnd_mrr_incr_refresh_ov_sit_s_tmsht_item", "StringEquals": "Y", "Next": "PASS SIT_S_TMSHT_ITEM"}], "Default": "LOAD SIT_S_TMSHT_ITEM"}, "LOAD SIT_S_TMSHT_ITEM": {"Type": "Task", "ResultPath": "$.SIT_S_TMSHT_ITEM", "Resource": "arn:aws:states:::glue:startJobRun.sync", "Parameters": {"JobName": "job_lnd_mrr_incr_refresh_ov_sit_s_tmsht_item", "Arguments": {"--batch_number.$": "$.INPUT.BATCH_NUMBER"}}, "Retry": [{"ErrorEquals": ["States.Timeout"], "MaxAttempts": 3, "IntervalSeconds": 60, "BackoffRate": 2}], "Catch": [{"ErrorEquals": ["States.TaskFailed"], "Next": "SNS_SIT_S_TMSHT_ITEM_FAILED"}], "Next": "PASS SIT_S_TMSHT_ITEM"}, "SNS_SIT_S_TMSHT_ITEM_FAILED": {"Type": "Task", "Resource": "arn:aws:states:::sns:publish", "Parameters": {"TopicArn": "arn:aws:sns:us-east-1:541574621075:ODP_SFN_FAILURE", "Message.$": "$.Cause", "Subject": " AWS Glue job for SNS_SIT_S_TMSHT_ITEM Failed!"}, "Next": "SIT_S_TMSHT_ITEM_ACTIVITY"}, "SIT_S_TMSHT_ITEM_ACTIVITY": {"Type": "Task", "Resource": "arn:aws:states:us-east-1:541574621075:activity:COMPACTION_SIT_S_TMSHT_ITEM_ACTIVITY", "End": true}, "PASS SIT_S_TMSHT_ITEM": {"Type": "Pass", "End": true}}}]}, "Completed": {"Type": "Pass", "InputPath": "$.SKIP_LAMBDA", "Next": "SNS_SIT_COMPACTION_SUCCESS"}, "SNS_SIT_COMPACTION_SUCCESS": {"Type": "Task", "InputPath": "$", "ResultPath": "$.snsResult", "Resource": "arn:aws:states:::sns:publish", "Parameters": {"TopicArn": "arn:aws:sns:us-east-1:541574621075:ODP_SFN_SUCCESS", "Message": {"Subject": "AWS Step function for COMPACTION_SIT completed successfully!!"}}, "End": true}}}