{"Name": "QA_job_mrr_fnd_gl_es_segmnt2_d_drm", "Role": "arn:aws:iam::541574621075:role/ODP-US-Innovation-AWSServiceRole", "CreatedOn": "2020-03-09 11:41:54.499000+00:00", "LastModifiedOn": "2020-03-09 11:41:54.499000+00:00", "ExecutionProperty": {"MaxConcurrentRuns": 1}, "Command": {"Name": "glueetl", "ScriptLocation": "s3://odp-us-innovation-raw/nti-developers/ODP_test/job_mrr_fnd_gl_es_segmnt2_d_drm", "PythonVersion": "3"}, "DefaultArguments": {"--TempDir": "s3://odp-us-innovation-raw/nti-developers/ODP_test", "--glue_conn": "TestRedshift", "--job-bookmark-option": "job-bookmark-disable", "--job-language": "python", "--natural_key": "account_key", "--rs_db": "usinnovationredshift", "--rs_stage_schema": "hdl_services_etl_stage", "--rs_stage_table": "gl_es_segmnt2_dh_stage", "--rs_target_schema": "hdl_cfd_data", "--rs_target_table": "gl_es_segmnt2_dh", "--source_db": "db_mrr_drm", "--source_system": "DRM", "--source_table_1": "hcbi_es_hier_account_alt", "--source_table_2": "hcbi_es_prop_account_alt", "--stage_cols": "account_key, account_desc, alt_cc_nam, levl_proprty, levl1_key, levl1_id, levl1_desc, levl2_key, levl2_id, levl2_desc, levl3_key, levl3_id, levl3_desc, levl4_key, levl4_id, levl4_desc, levl5_key, levl5_id, levl5_desc, levl6_key, levl6_id, levl6_desc, levl7_key, levl7_id, levl7_desc, levl8_key, levl8_id, levl8_desc, levl9_key, levl9_id, levl9_desc, levl10_key, levl10_id, levl10_desc, levl11_key, levl11_id, levl11_desc, levl12_key, levl12_id, levl12_desc, node_status, master_flg, master_flg_desc, source_name, posting_agent, data_origin, load_dtm, update_dtm, source_update_dtm, source_creation_dtm, gl_es_segmnt2_dh_md5, start_dtm, end_dtm, current_flag_ind, deleted_flag_ind", "--target_cols": "account_key, account_desc, alt_cc_nam, levl_proprty, levl1_key, levl1_id, levl1_desc, levl2_key, levl2_id, levl2_desc, levl3_key, levl3_id, levl3_desc, levl4_key, levl4_id, levl4_desc, levl5_key, levl5_id, levl5_desc, levl6_key, levl6_id, levl6_desc, levl7_key, levl7_id, levl7_desc, levl8_key, levl8_id, levl8_desc, levl9_key, levl9_id, levl9_desc, levl10_key, levl10_id, levl10_desc, levl11_key, levl11_id, levl11_desc, levl12_key, levl12_id, levl12_desc, node_status, master_flg, master_flg_desc, source_name, posting_agent, data_origin, load_dtm, update_dtm, source_update_dtm, source_creation_dtm, gl_es_segmnt2_dh_md5, start_dtm, end_dtm, current_flag_ind, deleted_flag_ind"}, "Connections": {"Connections": ["TestRedshift"]}, "MaxRetries": 0, "AllocatedCapacity": 11, "Timeout": 60, "MaxCapacity": 11.0, "GlueVersion": "1.0"}