{"stateMachineArn": "arn:aws:states:us-east-1:245792935030:stateMachine:MAPP_MASTER_CONTINGENCY_SCHEDULE", "name": "MAPP_MASTER_CONTINGENCY_SCHEDULE", "status": "ACTIVE", "definition": "{\n    \"StartAt\": \"MAPP_MASTER_CONTINGENCY_SCHEDULE\",\n    \"States\": {\n        \"MAPP_MASTER_CONTINGENCY_SCHEDULE\": {\n            \"Type\": \"Pass\",\n            \"Result\": \"$\",\n            \"Next\": \"CHECK CONTINGENCY RUN\"\n        },\n        \"CHECK CONTINGENCY RUN\": {\n            \"Type\": \"Task\",\n            \"Parameters\": {\n                \"DDB_KEY_TO_UPDATE\": \"skip_contingency_finished_flag\"\n            },\n            \"Resource\": \"arn:aws:lambda:us-east-1:245792935030:function:mapp_daily_run_schedule_update\",\n            \"Catch\": [\n                {\n                    \"ErrorEquals\": [\n                        \"ZeroDivisionError\"\n                    ],\n                    \"Next\": \"SNS_CONTINGENCY_CHECK_FAILED\"\n                }\n            ],\n            \"Next\": \"UPDATE CONTINGENCY LAMBDA\"\n        },\n        \"UPDATE CONTINGENCY LAMBDA\": {\n            \"Type\": \"Task\",\n            \"InputPath\": \"$\",\n            \"ResultPath\": \"$\",\n            \"Parameters\": {\n                \"DDB_KEY_TO_UPDATE\": \"contingency_finished_flag\"\n            },\n            \"Resource\": \"arn:aws:lambda:us-east-1:245792935030:function:mapp_daily_run_schedule_update\",\n            \"Next\": \"UPDATE SNAPSHOT LAMBDA\"\n        },\n        \"UPDATE SNAPSHOT LAMBDA\": {\n            \"Type\": \"Task\",\n            \"InputPath\": \"$\",\n            \"ResultPath\": \"$\",\n            \"Parameters\": {\n                \"DDB_KEY_TO_UPDATE\": \"contigency_null\"\n            },\n            \"Resource\": \"arn:aws:lambda:us-east-1:245792935030:function:mapp_snapshot_lock\",\n            \"End\": true\n        },\n        \"FAIL_SCHEDULE\": {\n            \"Type\": \"Fail\",\n            \"Cause\": \"Invalid response.\",\n            \"Error\": \"ErrorA\"\n        },\n        \"SNS_CONTINGENCY_CHECK_FAILED\": {\n            \"Type\": \"Task\",\n            \"Resource\": \"arn:aws:states:::sns:publish\",\n            \"Parameters\": {\n                \"TopicArn\": \"arn:aws:sns:us-east-1:245792935030:ODP_SFN_FAILURE\",\n                \"Message.$\": \"$.Cause\",\n                \"Subject\": \"MAPP CONTINGENCY job cannot be executed as other MAPP jobs are running !\"\n            },\n            \"Next\": \"FAIL_SCHEDULE\"\n        }\n    }\n}", "roleArn": "arn:aws:iam::245792935030:role/ODP-US-Prod-AWSServiceRole", "type": "STANDARD", "creationDate": "2020-07-15 06:32:53.506000+00:00", "loggingConfiguration": {"level": "ALL", "includeExecutionData": true, "destinations": [{"cloudWatchLogsLogGroup": {"logGroupArn": "arn:aws:logs:us-east-1:245792935030:log-group:/aws/states/MAPP_MASTER_CONTINGENCY_SCHEDULE-Logs:*"}}]}, "ResponseMetadata": {"RequestId": "a3b09725-4479-42aa-8b7f-fe7f1a688b5a", "HTTPStatusCode": 200, "HTTPHeaders": {"x-amzn-requestid": "a3b09725-4479-42aa-8b7f-fe7f1a688b5a", "content-type": "application/x-amz-json-1.0", "content-length": "2929"}, "RetryAttempts": 0}}