{"stateMachineArn": "arn:aws:states:us-east-1:245792935030:stateMachine:OUTLIERS_CDS_HC_REL_SR_FIELD", "name": "OUTLIERS_CDS_HC_REL_SR_FIELD", "status": "ACTIVE", "definition": "{\n    \"StartAt\": \"START OUTLIERS_CDS_HC_REL_SR_FIELD SCHEDULE\",\n    \"States\": {\n        \"START OUTLIERS_CDS_HC_REL_SR_FIELD SCHEDULE\": {\n            \"Type\": \"Pass\",\n            \"InputPath\": \"$\",\n            \"OutputPath\": \"$\",\n            \"Next\": \"CDS_HC_REL_SOL_SR_FIELD\"\n        },\n        \"CDS_HC_REL_SOL_SR_FIELD\": {\n            \"Type\": \"Choice\",\n            \"Choices\": [\n                {\n                    \"Variable\": \"$.INPUT.CDS_HC_REL_SOL_SR_FIELD\",\n                    \"StringEquals\": \"Y\",\n                    \"Next\": \"SKIP CDS_HC_REL_SOL_SR_FIELD\"\n                }\n            ],\n            \"Default\": \"LOAD CDS_HC_REL_SOL_SR_FIELD\"\n        },\n        \"LOAD CDS_HC_REL_SOL_SR_FIELD\": {\n            \"Type\": \"Task\",\n            \"InputPath\": \"$\",\n            \"ResultPath\": \"$.CDS_HC_REL_SOL_SR_FIELD\",\n            \"Resource\": \"arn:aws:states:::glue:startJobRun.sync\",\n            \"Parameters\": {\n                \"JobName\": \"job_mrr_entity_cds_rs_proc\",\n                \"Arguments\": {\n                    \"--rs_proc_name\": \"hdl_services_sp.sp_hc_rel_sr_field_load()\"\n                }\n            },\n            \"Retry\": [\n                {\n                    \"ErrorEquals\": [\n                        \"States.Timeout\"\n                    ],\n                    \"MaxAttempts\": 3,\n                    \"IntervalSeconds\": 60,\n                    \"BackoffRate\": 2\n                }\n            ],\n            \"Catch\": [\n                {\n                    \"ErrorEquals\": [\n                        \"States.TaskFailed\"\n                    ],\n                    \"Next\": \"SNS_CDS_HC_REL_SOL_SR_FIELD_FAILED\"\n                }\n            ],\n            \"Next\": \"SKIP CDS_HC_REL_SOL_SR_FIELD\"\n        },\n        \"SNS_CDS_HC_REL_SOL_SR_FIELD_FAILED\": {\n            \"Type\": \"Task\",\n            \"Resource\": \"arn:aws:states:::sns:publish\",\n            \"Parameters\": {\n                \"TopicArn\": \"arn:aws:sns:us-east-1:245792935030:ODP_SFN_FAILURE\",\n                \"Message.$\": \"$.Cause\",\n                \"Subject\": \"AWS GLUE SHELL JOB FOR CDS_HC_REL_SOL_SR_FIELD FAILED!\"\n            },\n            \"End\": false\n        },\n        \"SKIP CDS_HC_REL_SOL_SR_FIELD\": {\n            \"Type\": \"Pass\",\n            \"Next\": \"Completed\"\n        },\n        \"Completed\": {\n            \"Type\": \"Pass\",\n            \"Next\": \"SNS_CDS_HC_REL_SOL_SR_FIELD_SUCCESS\"\n        },\n        \"SNS_CDS_HC_REL_SOL_SR_FIELD_SUCCESS\": {\n            \"Type\": \"Task\",\n            \"Resource\": \"arn:aws:states:::sns:publish\",\n            \"Parameters\": {\n                \"TopicArn\": \"arn:aws:sns:us-east-1:245792935030:ODP_SFN_SUCCESS\",\n                \"Message\": {\n                    \"Subject\": \"AWS Step function for SNS_CDS_HC_REL_SOL_SR_FIELD_SUCCESS completed successfully!!\"\n                }\n            },\n            \"End\": true\n        }\n    }\n}", "roleArn": "arn:aws:iam::245792935030:role/ODP-US-Prod-AWSServiceRole", "type": "STANDARD", "creationDate": "2020-07-02 18:06:52.146000+00:00", "loggingConfiguration": {"level": "ALL", "includeExecutionData": true, "destinations": [{"cloudWatchLogsLogGroup": {"logGroupArn": "arn:aws:logs:us-east-1:245792935030:log-group:/aws/states/OUTLIERS_CDS_HC_REL_SR_FIELD-Logs:*"}}]}, "ResponseMetadata": {"RequestId": "4171ce5d-6b20-4339-83c2-fb483067236f", "HTTPStatusCode": 200, "HTTPHeaders": {"x-amzn-requestid": "4171ce5d-6b20-4339-83c2-fb483067236f", "content-type": "application/x-amz-json-1.0", "content-length": "3652"}, "RetryAttempts": 0}}