{
    "Name": "job_lnd_mrr_incr_refresh_ov_gla_gl_jornl_det_all_fx2",
    "Role": "arn:aws:iam::245792935030:role/ODP-US-Prod-AWSServiceRole",
    "CreatedOn": "2020-04-30 20:07:39.934000+05:30",
    "LastModifiedOn": "2020-05-05 12:09:00.614000+05:30",
    "ExecutionProperty": {
        "MaxConcurrentRuns": 1
    },
    "Command": {
        "Name": "glueetl",
        "ScriptLocation": "s3://odp-us-prod-raw/servicesuite/ODP/Compaction/src/job_lnd_mrr_incr_refresh_op_val.py",
        "PythonVersion": "3"
    },
    "DefaultArguments": {
        "--TempDir": "s3://odp-us-prod-raw/servicesuite/tempDir/",
        "--batch_number": "0",
        "--bucket_name": "odp-us-prod-raw",
        "--enable-metrics": "",
        "--file_split": "64",
        "--history_reload": "N",
        "--job-bookmark-option": "job-bookmark-enable",
        "--job-language": "python",
        "--mrr_db": "db_compacted_mrr_gla",
        "--mrr_table_name": "gl_jornl_det_all_fx2",
        "--raw_db": "db_lnd_gla",
        "--raw_table_name": "gl_jornl_det_all_fx2",
        "--src_system": "gla"
    },
    "Connections": {
        "Connections": [
            "US-ProdPeeringSubnetRedshitConnection"
        ]
    },
    "MaxRetries": 0,
    "AllocatedCapacity": 5,
    "Timeout": 2880,
    "MaxCapacity": 10,
    "WorkerType": "G.1X",
    "NumberOfWorkers": 5,
    "GlueVersion": "1.0"
}