[{"Id": "Id10193562341013", "Arn": "arn:aws:states:us-east-1:245792935030:stateMachine:MUST", "RoleArn": "arn:aws:iam::245792935030:role/ODP-US-Prod-AWSServiceRole", "Input": "{   \"STEPFUNCTION_NAME\": \"MUST\",   \"JOBS\": {     \"job_mrr_fnd_geo_addr_d_must\": \"must/musadmin/site/\",     \"job_mrr_fnd_prd_main_d_must\": \"must/musadmin/parts/\",     \"job_mrr_fnd_prt_persn_d_must\": \"must/musadmin/syst/\",     \"job_mrr_fnd_prt_cust_d_must\": \"must/musadmin/cust_acc/\"   },   \"SKIP_FLAG\": {     \"getJobDtls_sfn\": \"N\",     \"job_mrr_fnd_prd_main_d_must\": \"N\",     \"job_mrr_fnd_geo_addr_d_must\": \"N\",     \"job_mrr_fnd_prt_cust_d_must\": \"N\",     \"job_mrr_fnd_prt_persn_d_must\": \"N\"   } }"}]