{"Name": "us-prod-daasbatchextract-start-ci-extracts", "Arn": "arn:aws:events:us-east-1:245792935030:rule/us-prod-daasbatchextract-start-ci-extracts", "ScheduleExpression": "cron(00 12 1-2 * ? *)", "State": "ENABLED", "EventBusName": "default", "ResponseMetadata": {"RequestId": "2035d066-e241-4f69-b370-cb1f0408f9d5", "HTTPStatusCode": 200, "HTTPHeaders": {"x-amzn-requestid": "2035d066-e241-4f69-b370-cb1f0408f9d5", "content-type": "application/x-amz-json-1.1", "content-length": "235", "date": "Fri, 24 Jul 2020 08:43:18 GMT"}, "RetryAttempts": 0}}