{"Name": "ODP_CW_DAILY_SCHEDULE_TRACK_B_COMPLETE", "Arn": "arn:aws:events:us-east-1:541574621075:rule/ODP_CW_DAILY_SCHEDULE_TRACK_B_COMPLETE", "EventPattern": "{\"source\":[\"aws.states\"],\"detail-type\":[\"Step Functions Execution Status Change\"],\"detail\":{\"status\":[\"SUCCEEDED\"],\"stateMachineArn\":[\"arn:aws:states:us-east-1:245792935030:stateMachine:GLA_COMPACTION\"]}}", "State": "DISABLED", "Description": "TRACK B COMPLETED", "EventBusName": "default", "ResponseMetadata": {"RequestId": "750dbf6b-c7f6-4b90-bcd5-463754c0daec", "HTTPStatusCode": 200, "HTTPHeaders": {"x-amzn-requestid": "750dbf6b-c7f6-4b90-bcd5-463754c0daec", "content-type": "application/x-amz-json-1.1", "content-length": "457", "date": "Wed, 22 Jul 2020 18:13:45 GMT"}, "RetryAttempts": 0}}