{"Name": "ODP_CW_DAILY_SCHEDULE_TRACK_F3", "Arn": "arn:aws:events:us-east-1:541574621075:rule/ODP_CW_DAILY_SCHEDULE_TRACK_F3", "EventPattern": "{\"source\":[\"aws.states\"],\"detail-type\":[\"Step Functions Execution Status Change\"],\"detail\":{\"status\":[\"SUCCEEDED\"],\"stateMachineArn\":[\"arn:aws:states:us-east-1:245792935030:stateMachine:RULE_STUDIO_COMPACTION\"]}}", "State": "DISABLED", "Description": "Target : GIB_COMPACTION", "EventBusName": "default", "ResponseMetadata": {"RequestId": "13a1ae33-0009-42ed-a1c5-14a4838ac350", "HTTPStatusCode": 200, "HTTPHeaders": {"x-amzn-requestid": "13a1ae33-0009-42ed-a1c5-14a4838ac350", "content-type": "application/x-amz-json-1.1", "content-length": "455", "date": "Wed, 22 Jul 2020 18:14:03 GMT"}, "RetryAttempts": 0}}